pyclearsilver
