Metadata-Version: 1.0
Name: pyclearsilver
Version: 1.0
Summary: Python modules for building web applications with Clearsilver
Home-page: UNKNOWN
Author: Python Clearsilver developers
Author-email: jeske@willowmail.com,hassan@willowmail.com
License: Apache
Download-URL: http://www.willowmail.com/clearsilver/pyclearsilver-1.0.tar.gz
Platform: ALL
Classifier: Intended Audience :: Developers
Classifier: Programming Language :: Python
